{
  "file-webkitrelativepath": "Type: USVString",
  "htmlinputelement-webkitdirectory": "Type: boolean",
  "htmlinputelement-webkitentries": "Type: [object Object]",
  "datatransferitem-webkitgetasentry": "Type: FileSystemEntry",
  "errorcallback": "No description available.",
  "filesystementry-isfile": "Type: boolean",
  "filesystementry-isdirectory": "Type: boolean",
  "filesystementry-name": "Type: USVString",
  "filesystementry-fullpath": "Type: USVString",
  "filesystementry-filesystem": "Type: FileSystem",
  "filesystementry-getparent": "Type: undefined",
  "filesystemdirectoryentry-createreader": "Type: FileSystemDirectoryReader",
  "filesystemdirectoryentry-getfile": "Type: undefined",
  "filesystemdirectoryentry-getdirectory": "Type: undefined",
  "filesystemflags-create": "Type: boolean",
  "filesystemflags-exclusive": "Type: boolean",
  "filesystementrycallback": "No description available.",
  "filesystemdirectoryreader-readentries": "Type: undefined",
  "filesystementriescallback": "No description available.",
  "filesystemfileentry-file": "Type: undefined",
  "filecallback": "No description available.",
  "filesystem-name": "Type: USVString",
  "filesystem-root": "Type: FileSystemDirectoryEntry"
}